[{"__type__":"cc.Prefab","_name":"ShowPrefab","data":{"__id__":1},"optimizationPolicy":1},{"__type__":"cc.Node","_name":"ShowPrefab","_children":[{"__id__":2},{"__id__":11}],"_components":[{"__type__":"456dblGxoFMLoZkhYSwUjmB","node":{"__id__":1},"connonNode":{"__id__":2}},{"__type__":"cc.Mask","node":{"__id__":1},"_materials":[{"__uuid__":"ecpdLyjvZBwrvm+cedCcQy"}]}],"_prefab":{"__type__":"cc.PrefabInfo","root":{"__id__":1},"asset":{"__uuid__":"f6j9NC9MlChKmaJhVDOQGZ"},"fileId":"30ediL951JGYUPgHB1rd5d"},"_contentSize":{"__type__":"cc.Size","width":684,"height":265},"_anchorPoint":{"__type__":"cc.Vec2"},"_trs":{"__type__":"TypedArray","ctor":"Float64Array","array":[-342,-340,0,0,0,0,1,1,1,1]}},{"__type__":"cc.Node","_name":"Connon","_parent":{"__id__":1},"_children":[{"__id__":3},{"__id__":5},{"__id__":7},{"__id__":9},{"__id__":12},{"__id__":13}],"_components":[{"__type__":"cc.Widget","node":{"__id__":2},"alignMode":0,"_alignFlags":4,"_bottom":6.5},{"__id__":14},{"__type__":"787f2nl5z5GwrbamdjnghA1","node":{"__id__":2},"bulletNode":{"__id__":11},"connonSprite":{"__id__":6},"bulletPrefab":[{"__uuid__":"47v34lyehKCq/tV7r+Coda"},{"__uuid__":"65jn97aC5JKZsyETkJgrFd"},{"__uuid__":"9c9eQpIHtInIoAaYM9AfFr"},{"__uuid__":"53qE23bmNNzLZsvJ0ZfFZ1"}],"wheelSprite":{"__id__":8},"connonAtlas":{"__uuid__":"388Fh4g7FB65J/Ym6OMmc0"},"fire":{"__id__":4},"subConnon":{"__id__":10},"funnelLeftNode":{"__id__":12},"funnelRightNode":{"__id__":13},"invincibleAin":{"__id__":14},"maxSpeed":35,"aSpeed":8}],"_prefab":{"__type__":"cc.PrefabInfo","root":{"__id__":1},"asset":{"__uuid__":"f6j9NC9MlChKmaJhVDOQGZ"},"fileId":"8a4cR61Z9BTKwaaR17IDUV"},"_contentSize":{"__type__":"cc.Size","width":120,"height":120},"_trs":{"__type__":"TypedArray","ctor":"Float64Array","array":[342,66.5,0,0,0,0,1,1,1,1]},"_groupIndex":3,"groupIndex":3},{"__type__":"cc.Node","_name":"fire","_parent":{"__id__":2},"_components":[{"__id__":4}],"_prefab":{"__type__":"cc.PrefabInfo","root":{"__id__":1},"asset":{"__uuid__":"f6j9NC9MlChKmaJhVDOQGZ"},"fileId":"084JczltpLN7sBAUa0rBtl"},"_contentSize":{"__type__":"cc.Size","width":120,"height":160},"_trs":{"__type__":"TypedArray","ctor":"Float64Array","array":[0.7,56.4,0,0,0,0,1,0.6,0.6,1]}},{"__type__":"cc.Sprite","node":{"__id__":3},"_materials":[{"__uuid__":"ecpdLyjvZBwrvm+cedCcQy"}],"_sizeMode":0,"_isTrimmedMode":false},{"__type__":"cc.Node","_name":"connon","_parent":{"__id__":2},"_components":[{"__id__":6}],"_prefab":{"__type__":"cc.PrefabInfo","root":{"__id__":1},"asset":{"__uuid__":"f6j9NC9MlChKmaJhVDOQGZ"},"fileId":"16di5lWsRALYGyo/RYMyXw"},"_contentSize":{"__type__":"cc.Size","width":120,"height":120},"_trs":{"__type__":"TypedArray","ctor":"Float64Array","array":[0,0,0,0,0,0,1,1,1,1]}},{"__type__":"cc.Sprite","node":{"__id__":5},"_materials":[{"__uuid__":"ecpdLyjvZBwrvm+cedCcQy"}],"_spriteFrame":{"__uuid__":"61SpMCGANKMaEx63uDGDoI"},"_sizeMode":0,"_isTrimmedMode":false},{"__type__":"cc.Node","_name":"wheel","_parent":{"__id__":2},"_components":[{"__id__":8}],"_prefab":{"__type__":"cc.PrefabInfo","root":{"__id__":1},"asset":{"__uuid__":"f6j9NC9MlChKmaJhVDOQGZ"},"fileId":"12QM3nOAVELKRA7zyvJYAQ"},"_contentSize":{"__type__":"cc.Size","width":120,"height":120},"_trs":{"__type__":"TypedArray","ctor":"Float64Array","array":[0,0,0,0,0,0,1,1,1,1]}},{"__type__":"cc.Sprite","node":{"__id__":7},"_materials":[{"__uuid__":"ecpdLyjvZBwrvm+cedCcQy"}],"_spriteFrame":{"__uuid__":"a6+Qt5B45NvYbt8Al3fFWY"},"_sizeMode":0,"_isTrimmedMode":false},{"__type__":"cc.Node","_name":"subConnon","_parent":{"__id__":2},"_components":[{"__id__":10},{"__type__":"77bf6tHuaZOnaFedCV+rgY3","node":{"__id__":9},"bulletNode":{"__id__":11},"connonSprite":{"__id__":10}}],"_prefab":{"__type__":"cc.PrefabInfo","root":{"__id__":1},"asset":{"__uuid__":"f6j9NC9MlChKmaJhVDOQGZ"},"fileId":"c61yGobv5Gbrm7nz6hIMPF"},"_contentSize":{"__type__":"cc.Size","width":120,"height":120},"_trs":{"__type__":"TypedArray","ctor":"Float64Array","array":[0,0,0,0,0,0,1,1,1,1]}},{"__type__":"cc.Sprite","node":{"__id__":9},"_materials":[{"__uuid__":"ecpdLyjvZBwrvm+cedCcQy"}],"_spriteFrame":{"__uuid__":"8c+vGRYsJLHLYG+DXJLcah"},"_sizeMode":0,"_isTrimmedMode":false},{"__type__":"cc.Node","_name":"bulletNode","_parent":{"__id__":1},"_prefab":{"__type__":"cc.PrefabInfo","root":{"__id__":1},"asset":{"__uuid__":"f6j9NC9MlChKmaJhVDOQGZ"},"fileId":"87AjMVx0pPAaM4Za/2vrbi"},"_contentSize":{"__type__":"cc.Size","width":684,"height":265},"_anchorPoint":{"__type__":"cc.Vec2"},"_trs":{"__type__":"TypedArray","ctor":"Float64Array","array":[0,0,0,0,0,0,1,1,1,1]}},{"__type__":"cc.Node","_name":"funnelLeftNode","_parent":{"__id__":2},"_prefab":{"__type__":"cc.PrefabInfo","root":{"__id__":1},"asset":{"__uuid__":"f6j9NC9MlChKmaJhVDOQGZ"},"fileId":"19/0pwY+hOorIY+XqiTZpL"},"_contentSize":{"__type__":"cc.Size","width":72,"height":79},"_trs":{"__type__":"TypedArray","ctor":"Float64Array","array":[-104,-13,0,0,0,0,1,1,1,1]}},{"__type__":"cc.Node","_name":"funnelRightNode","_parent":{"__id__":2},"_prefab":{"__type__":"cc.PrefabInfo","root":{"__id__":1},"asset":{"__uuid__":"f6j9NC9MlChKmaJhVDOQGZ"},"fileId":"94LBmXvatJpKYYn01hVI7C"},"_contentSize":{"__type__":"cc.Size","width":72,"height":79},"_trs":{"__type__":"TypedArray","ctor":"Float64Array","array":[104,-13,0,0,0,0,1,1,1,1]}},{"__type__":"cc.Animation","node":{"__id__":2},"_clips":[{"__uuid__":"e0OPgKoCdFI62rcNV1Zu03"},{"__uuid__":"8enB2MkdtFiLhDDcwPnc+5"}]}]